Metadata-Version: 1.0
Name: iqyocr
Version: 0.0.2
Summary: iqy ocr for uiautomaotr2
Home-page: http://www.iqiyi.com
Author: yuyinweiliao
Author-email: yuyinweiliao@163.com
License: UNKNOWN
Platform: UNKNOWN
